{
  "project_info": {
    "project_number": "392187918962",
    "project_id": "quizapp-4e37a",
    "storage_bucket": "quizapp-4e37a.firebasestorage.app"
  },
  "client": [
    {
      "client_info": {
        "mobilesdk_app_id": "1:392187918962:android:7f563598b429aadc3760eb",
        "android_client_info": {
          "package_name": "com.example.quiz_app"
        }
      },
      "oauth_client": [],
      "api_key": [
        {
          "current_key": "AIzaSyC2lX20H2_L_q6Kc2LXypT9A4TFjKuEiOk"
        }
      ],
      "services": {
        "appinvite_service": {
          "other_platform_oauth_client": []
        }
      }
    }
  ],
  "configuration_version": "1"
}